quantuloop_quest/__init__.py
quantuloop_quest/libquloop_quest.so
quantuloop_quest-0.2.2.dist-info/METADATA
quantuloop_quest-0.2.2.dist-info/WHEEL
quantuloop_quest-0.2.2.dist-info/top_level.txt
quantuloop_quest-0.2.2.dist-info/RECORD
quantuloop_quest.libs/libgomp-a34b3233.so.1.0.0
quantuloop_quest.libs/libql_quest-20ed9cdd.so
