Metadata-Version: 2.1
Name: quantuloop-quest
Version: 0.2.2
Summary: QuEST interface for the Ket Quantum Programming Language.
Author: Quantuloop
License: Quantuloop Quantum Simulator Suite EULA
Keywords: quantum computer,quantum programming,quantum simulator
Platform: linux
Classifier: Intended Audience :: Science/Research
Classifier: Operating System :: POSIX :: Linux
Classifier: Programming Language :: Python :: 3
Requires-Python: >=3.7
Requires-Dist: PyJWT (>=2.4.0)
Requires-Dist: cryptography (>=37.0)
Requires-Dist: ket-lang (<0.7.0,>=0.6.1)
